phonexia/grpc/common/__init__.py
phonexia/grpc/common/core_pb2.py
phonexia/grpc/common/core_pb2.pyi
phonexia/grpc/common/core_pb2_grpc.py
phonexia/grpc/common/health_check_pb2.py
phonexia/grpc/common/health_check_pb2.pyi
phonexia/grpc/common/health_check_pb2_grpc.py
phonexia/grpc/common/licensing_pb2.py
phonexia/grpc/common/licensing_pb2.pyi
phonexia/grpc/common/licensing_pb2_grpc.py
phonexia/grpc/common/status_pb2.py
phonexia/grpc/common/status_pb2.pyi
phonexia/grpc/common/status_pb2_grpc.py
phonexia/grpc/technologies/__init__.py
phonexia/grpc/technologies/age_estimation/__init__.py
phonexia/grpc/technologies/age_estimation/v1/__init__.py
phonexia/grpc/technologies/age_estimation/v1/age_estimation_pb2.py
phonexia/grpc/technologies/age_estimation/v1/age_estimation_pb2.pyi
phonexia/grpc/technologies/age_estimation/v1/age_estimation_pb2_grpc.py
phonexia/grpc/technologies/audio_manipulation_detection/__init__.py
phonexia/grpc/technologies/audio_manipulation_detection/experimental/__init__.py
phonexia/grpc/technologies/audio_manipulation_detection/experimental/audio_manipulation_detection_pb2.py
phonexia/grpc/technologies/audio_manipulation_detection/experimental/audio_manipulation_detection_pb2.pyi
phonexia/grpc/technologies/audio_manipulation_detection/experimental/audio_manipulation_detection_pb2_grpc.py
phonexia/grpc/technologies/audio_quality_estimation/__init__.py
phonexia/grpc/technologies/audio_quality_estimation/v1/__init__.py
phonexia/grpc/technologies/audio_quality_estimation/v1/audio_quality_estimation_pb2.py
phonexia/grpc/technologies/audio_quality_estimation/v1/audio_quality_estimation_pb2.pyi
phonexia/grpc/technologies/audio_quality_estimation/v1/audio_quality_estimation_pb2_grpc.py
phonexia/grpc/technologies/deepfake_detection/__init__.py
phonexia/grpc/technologies/deepfake_detection/v1/__init__.py
phonexia/grpc/technologies/deepfake_detection/v1/deepfake_detection_pb2.py
phonexia/grpc/technologies/deepfake_detection/v1/deepfake_detection_pb2.pyi
phonexia_grpc-2.27.1.dist-info/LICENSE
phonexia_grpc-2.27.1.dist-info/METADATA
phonexia_grpc-2.27.1.dist-info/WHEEL
phonexia_grpc-2.27.1.dist-info/RECORD
