Metadata-Version: 2.1
Name: phonexia-grpc
Version: 2.27.1
Summary: Library for communication with microservices developed by phonexia using grpc application interface.
License: Apache-2.0
Keywords: grpc,voice,voice-biometry,speech,language,STT,whisper
Author: Phonexia s.r.o.
Author-email: info@phonexia.com
Requires-Python: >=3.9,<4.0
Classifier: License :: OSI Approved :: Apache Software License
Classifier: Programming Language :: Python :: 3
Classifier: Programming Language :: Python :: 3.9
Classifier: Programming Language :: Python :: 3.10
Classifier: Programming Language :: Python :: 3.11
Classifier: Programming Language :: Python :: 3.12
Requires-Dist: grpc-stubs (>=1.53.0.2,<2.0.0.0)
Requires-Dist: grpcio (>=1.75.0,<2.0.0)
Requires-Dist: mypy-protobuf (>=3.5.0,<4.0.0)
Requires-Dist: protobuf (>=6.0.0,<7.0.0)
Project-URL: Changelog, https://github.com/phonexia/protofiles/blob/main/CHANGELOG.md
Project-URL: Homepage, https://phonexia.com
Project-URL: Issues, https://phonexia.atlassian.net/servicedesk/customer/portal/15/group/20/create/40
Project-URL: Source, https://github.com/phonexia/protofiles
